trprimes/__init__.py
trprimes/truncp.py
trprimes/truncp_test.py
trprimes-0.1.1.dist-info/LICENSE
trprimes-0.1.1.dist-info/METADATA
trprimes-0.1.1.dist-info/WHEEL
trprimes-0.1.1.dist-info/top_level.txt
trprimes-0.1.1.dist-info/RECORD
