Metadata-Version: 2.1
Name: trprimes
Version: 0.1.1
Summary: Truncatable prime number generators
Home-page: https://github.com/harry-zuzan/trprimes
Author: Harry Zuzan
License: Unlicense
Keywords: prime numbers,truncatable
Platform: UNKNOWN
Classifier: Development Status :: 3 - Alpha
Classifier: Intended Audience :: Education
Classifier: Topic :: Scientific/Engineering :: Mathematics
Classifier: License :: OSI Approved :: The Unlicense (Unlicense)
Classifier: Programming Language :: Python
Classifier: Programming Language :: Python :: 3
Classifier: Programming Language :: Python :: 3.6
Classifier: Programming Language :: Python :: 3.7
Classifier: Programming Language :: Python :: 3.8
Classifier: Programming Language :: Python :: 3.9
Classifier: Programming Language :: Python :: 3 :: Only
Requires-Python: <4,>=3.6
Requires-Dist: sympy
